RC6/RC6.py
RC6/__init__.py
RC6-1.1.dist-info/METADATA
RC6-1.1.dist-info/WHEEL
RC6-1.1.dist-info/top_level.txt
RC6-1.1.dist-info/RECORD
