Metadata-Version: 2.1
Name: RC6
Version: 1.1
Summary: RC6 encode-decoder
Home-page: UNKNOWN
Author: Mikhail Bityutsky
Author-email: darmollive@gmail.com
License: BSD
Platform: UNKNOWN
Classifier: Development Status :: 3 - Alpha
Classifier: Environment :: Web Environment
Classifier: Intended Audience :: Developers
Classifier: License :: OSI Approved :: BSD License
Classifier: Operating System :: OS Independent
Classifier: Programming Language :: Python
